warcdb/__init__.py
warcdb/migrations.py
warcdb-0.2.2.dist-info/LICENSE
warcdb-0.2.2.dist-info/METADATA
warcdb-0.2.2.dist-info/WHEEL
warcdb-0.2.2.dist-info/entry_points.txt
warcdb-0.2.2.dist-info/RECORD
