Metadata-Version: 2.1
Name: warcdb
Version: 0.2.2
Summary: WarcDB: Web crawl data as SQLite databases
Home-page: https://github.com/Florents-Tselai/warcdb
License: Apache License, Version 2.0
Author: Florents Tselai
Author-email: florents@tselai.com
Requires-Python: >=3.9,<4.0
Classifier: Intended Audience :: Developers
Classifier: Intended Audience :: Science/Research
Classifier: License :: Other/Proprietary License
Classifier: Programming Language :: Python :: 3
Classifier: Programming Language :: Python :: 3.9
Classifier: Programming Language :: Python :: 3.10
Classifier: Programming Language :: Python :: 3.11
Requires-Dist: click (>=8.1,<9.0)
Requires-Dist: more-itertools (>=10.1,<11.0)
Requires-Dist: requests (>=2.31,<3.0)
Requires-Dist: sqlite-migrate (==0.1a2)
Requires-Dist: sqlite-utils (>=3.26,<4.0)
Requires-Dist: tqdm (>=4.66,<5.0)
Requires-Dist: warcio (>=1.7,<2.0)
Project-URL: Repository, https://github.com/Florents-Tselai/warcdb
